nlqf/__init__.py
nlqf/model.py
nlqf/model_filter.py
nlqf/rule_filter.py
nlqf-0.1.13.dist-info/LICENSE
nlqf-0.1.13.dist-info/METADATA
nlqf-0.1.13.dist-info/WHEEL
nlqf-0.1.13.dist-info/top_level.txt
nlqf-0.1.13.dist-info/RECORD
