Metadata-Version: 2.1
Name: nlqf
Version: 0.1.13
Summary: A tool for fittering code comments
Home-page: UNKNOWN
Author: Zhensu Sun
Author-email: zhensuuu@gmail.com
License: UNKNOWN
Platform: UNKNOWN
Classifier: Programming Language :: Python :: 3
Classifier: License :: OSI Approved :: MIT License
Requires-Dist: torch (==1.3.1)
Requires-Dist: numpy
Requires-Dist: sklearn
Requires-Dist: nltk
